pyvint/__init__.py
pyvint/core.py
pyvint/py.typed
pyvint-1.1.2.dist-info/LICENSE
pyvint-1.1.2.dist-info/WHEEL
pyvint-1.1.2.dist-info/METADATA
pyvint-1.1.2.dist-info/RECORD
