Metadata-Version: 2.1
Name: pyvint
Version: 1.1.2
Summary: A Python library for pure Python encoding and decoding of integers using Variable-Size Integer (VINT).
Keywords: vint,variable-size integer,integer
Author: osoken
Requires-Python: >=3.8
Classifier: Development Status :: 5 - Production/Stable
Classifier: Intended Audience :: Developers
Classifier: Operating System :: OS Independent
Classifier: Programming Language :: Python :: 3
Classifier: Programming Language :: Python :: 3.8
Classifier: Programming Language :: Python :: 3.9
Classifier: Programming Language :: Python :: 3.10
Classifier: Programming Language :: Python :: 3.11
Classifier: Programming Language :: Python :: 3.12
Requires-Dist: black ; extra == "dev"
Requires-Dist: flake8 ; extra == "dev"
Requires-Dist: pyproject-flake8 ; extra == "dev"
Requires-Dist: pytest ; extra == "dev"
Requires-Dist: mypy ; extra == "dev"
Requires-Dist: tox ; extra == "dev"
Requires-Dist: isort ; extra == "dev"
Requires-Dist: pytest-cov ; extra == "dev"
Requires-Dist: pytest-random-order ; extra == "dev"
Requires-Dist: mkdocs ; extra == "docs"
Requires-Dist: mkdocs-material ; extra == "docs"
Requires-Dist: mkdocstrings[python] ; extra == "docs"
Requires-Dist: mkdocs-include-markdown-plugin ; extra == "docs"
Project-URL: Documentation, https://osoken.github.io/pyvint/
Project-URL: Source, https://github.com/osoken/pyvint
Provides-Extra: dev
Provides-Extra: docs
